sid/__init__.py
sid/_version.py
sid/colors.py
sid/config.py
sid/contacts.py
sid/countdowns.py
sid/covid_epi_params.csv
sid/events.py
sid/initial_conditions.py
sid/matching_probabilities.py
sid/msm.py
sid/parse_model.py
sid/pathogenesis.py
sid/plotting.py
sid/policies.py
sid/rapid_tests.py
sid/seasonality.py
sid/shared.py
sid/simulate.py
sid/statistics.py
sid/susceptibility.py
sid/testing.py
sid/testing_allocation.py
sid/testing_demand.py
sid/testing_processing.py
sid/time.py
sid/update_states.py
sid/vaccination.py
sid/validation.py
sid/virus_strains.py
sid/visualize_simulation_results.py
sid_dev-0.0.10.dist-info/LICENSE
sid_dev-0.0.10.dist-info/METADATA
sid_dev-0.0.10.dist-info/WHEEL
sid_dev-0.0.10.dist-info/top_level.txt
sid_dev-0.0.10.dist-info/RECORD
