Metadata-Version: 2.1
Name: sid-dev
Version: 0.0.10
Summary: Simulate the spread of COVID-19 with different policies.
Home-page: https://github.com/covid-19-impact-lab/sid
Author: Janos Gabler, Tobias Raabe, Klara Roehrl
Author-email: janos.gabler@gmail.com
License: MIT
Project-URL: Changelog, https://sid-dev.readthedocs.io/en/latest/changes.html
Project-URL: Documentation, https://sid-dev.readthedocs.io/en/latest
Project-URL: Github, https://github.com/covid-19-impact-lab/sid
Project-URL: Tracker, https://github.com/covid-19-impact-lab/sid/issues
Platform: any
Classifier: Development Status :: 3 - Alpha
Classifier: Intended Audience :: Science/Research
Classifier: License :: OSI Approved :: MIT License
Classifier: Operating System :: OS Independent
Classifier: Programming Language :: Python :: 3
Classifier: Programming Language :: Python :: 3 :: Only
Classifier: Programming Language :: Python :: 3.6
Classifier: Programming Language :: Python :: 3.7
Classifier: Programming Language :: Python :: 3.8
Classifier: Programming Language :: Python :: 3.9
Classifier: Topic :: Scientific/Engineering
Requires-Python: >=3.6
License-File: LICENSE
Requires-Dist: bokeh
Requires-Dist: dask
Requires-Dist: fastparquet (!=0.6.1)
Requires-Dist: holoviews
Requires-Dist: matplotlib
Requires-Dist: numba (>=0.48)
Requires-Dist: numpy
Requires-Dist: pandas (>=1)
Requires-Dist: python-snappy
Requires-Dist: seaborn
Requires-Dist: tqdm
